setup.py
vaishnavi_indian_states_25/__init__.py
vaishnavi_indian_states_25/asgi.py
vaishnavi_indian_states_25/settings.py
vaishnavi_indian_states_25/urls.py
vaishnavi_indian_states_25/wsgi.py
vaishnavi_indian_states_25.egg-info/PKG-INFO
vaishnavi_indian_states_25.egg-info/SOURCES.txt
vaishnavi_indian_states_25.egg-info/dependency_links.txt
vaishnavi_indian_states_25.egg-info/requires.txt
vaishnavi_indian_states_25.egg-info/top_level.txt
vut1/__init__.py
vut1/admin.py
vut1/apps.py
vut1/fields.py
vut1/forms.py
vut1/models.py
vut1/states.py
vut1/tests.py
vut1/views.py
vut1/migrations/__init__.py